rshanker779_common/__init__.py
rshanker779_common/decorators.py
rshanker779_common/filesytem.py
rshanker779_common/logger.py
rshanker779_common/mixins/__init__.py
rshanker779_common/mixins/equals_mixin.py
rshanker779_common/mixins/json_mixin.py
rshanker779_common/mixins/string_mixin.py
rshanker779_common/profiler.py
rshanker779_common/scraping.py
rshanker779_common/system.py
rshanker779_common/threads.py
rshanker779_common-1.0.1.dist-info/METADATA
rshanker779_common-1.0.1.dist-info/WHEEL
rshanker779_common-1.0.1.dist-info/RECORD
