Metadata-Version: 2.1
Name: rshanker779-common
Version: 1.0.1
Summary: Common utilities
Author: Rohan Shanker
Author-email: rshanker779@gmail.com
Requires-Python: >=3.7,<4.0
Classifier: Programming Language :: Python :: 3
Classifier: Programming Language :: Python :: 3.7
Classifier: Programming Language :: Python :: 3.8
Classifier: Programming Language :: Python :: 3.9
Classifier: Programming Language :: Python :: 3.10
Classifier: Programming Language :: Python :: 3.11
Requires-Dist: requests (>=2.28.2)
Requires-Dist: snakeviz (>=2.1.1)
